ghief/__init__.py
ghief/__main__.py
ghief/backup_git_repository.py
ghief-0.1.3.dist-info/METADATA
ghief-0.1.3.dist-info/WHEEL
ghief-0.1.3.dist-info/entry_points.txt
ghief-0.1.3.dist-info/top_level.txt
ghief-0.1.3.dist-info/RECORD
