Metadata-Version: 2.1
Name: ghief
Version: 0.1.3
Summary: Git Backup Script
Home-page: https://github.com/MatthiasLohr/ghief
Author: Matthias Lohr
Author-email: matthias@lohr.me
License: UNKNOWN
Platform: UNKNOWN
Requires-Dist: pyyaml (>=4.2b1)
